smithy/__init__.py
smithy/admin.py
smithy/apps.py
smithy/helpers.py
smithy/models.py
smithy/urls.py
smithy/views.py
smithy/migrations/0001_initial.py
smithy/migrations/0002_auto_20190317_1052_squashed_0008_auto_20190317_1213.py
smithy/migrations/0003_auto_20190721_2004.py
smithy/migrations/0004_auto_20190721_2012.py
smithy/migrations/__init__.py
smithy/static/css/smithy.css
smithy/static/js/smithy.js
django_smithy-0.3.0.dist-info/AUTHORS.rst
django_smithy-0.3.0.dist-info/LICENSE
django_smithy-0.3.0.dist-info/METADATA
django_smithy-0.3.0.dist-info/WHEEL
django_smithy-0.3.0.dist-info/top_level.txt
django_smithy-0.3.0.dist-info/RECORD
