Metadata-Version: 2.1
Name: django-smithy
Version: 0.3.0
Summary: Craft HTTP requests in the Django Admin.
Home-page: https://github.com/jamiecounsell/django-smithy
Author: Jamie Counsell
Author-email: jamiecounsell@me.com
License: MIT
Keywords: django-smithy
Platform: UNKNOWN
Classifier: Development Status :: 3 - Alpha
Classifier: Framework :: Django :: 1.11
Classifier: Framework :: Django :: 2.0
Classifier: Intended Audience :: Developers
Classifier: License :: OSI Approved :: BSD License
Classifier: Natural Language :: English
Classifier: Programming Language :: Python :: 3
Classifier: Programming Language :: Python :: 3.4
Classifier: Programming Language :: Python :: 3.5
Classifier: Programming Language :: Python :: 3.6
Classifier: Programming Language :: Python :: 3.7
Requires-Dist: django-model-utils (>=2.0)
Requires-Dist: djangocodemirror
